[  { "text": "After a storm comes a calm.", "author": "Matthew Henry" },
  {
    "text": "You are never too old to set another goal or to dream a new dream.",
    "author": "C. S. Lewis"
  },
  {
    "text": "With the new day comes new strength and new thoughts.",
    "author": "Eleanor Roosevelt"
  },
  {
    "text": "The will to win, the desire to succeed, the urge to reach your full potential... these are the keys that will unlock the door to personal excellence.",
    "author": "Confucius"
  },
  {
    "text": "Our greatest weakness lies in giving up. The most certain way to succeed is always to try just one more time.",
    "author": "Thomas A. Edison"
}]