[  {
    "text": "I believe patriotism comes from the heart. Patriotism is voluntary. It is a feeling of loyalty and allegiance that is the result of knowledge and belief.",
    "author": "Jesse Ventura"
  },
  {
    "text": "Patriotism consists not in waving the flag, but in striving that our country shall be righteous as well as strong.",
    "author": "James Bryce"
  },
  {
    "text": "Patriotism is not a short and frenzied outburst of emotion but the tranquil and steady dedication of a lifetime.",
    "author": "Adlai Stevenson"
  },
  {
    "text": "There are those who wrap themselves in flags and blow the tinny trumpet of patriotism as a means of fooling the people.",
    "author": "George Galloway"
  },
  {
    "text": "I want to light the lights of patriotism.",
    "author": "Lech Walesa"
}]