[  {
    "text": "Dreams come true. Without that possibility, nature would not incite us to have them.",
    "author": "John Updike"
  },
  {
    "text": "Staying in one place is the best path to be taken over and surpassed by many.",
    "author": "Byron Pulsifer"
  },
  {
    "text": "Imagination will often carry us to worlds that never were. But without it we go nowhere.",
    "author": "Carl Sagan"
  },
  {
    "text": "When one door of happiness closes, another opens; but often we look so long at the closed door that we do not see the one which has been opened for us.",
    "author": "Helen Keller"
  },
  {
    "text": "A leader or a man of action in a crisis almost always acts subconsciously and then thinks of the reasons for his action.",
    "author": "Jawaharlal Nehru"
}]