[  {
    "text": "My attitude is that if you push me towards something that you think is a weakness, then I will turn that perceived weakness into a strength.",
    "author": "Michael Jordan"
  },
  {
    "text": "Weakness of attitude becomes weakness of character.",
    "author": "Albert Einstein"
  },
  {
    "text": "Nothing can stop the man with the right mental attitude from achieving his goal nothing on earth can help the man with the wrong mental attitude.",
    "author": "Thomas Jefferson"
  },
  {
    "text": "Attitude is a little thing that makes a big difference.",
    "author": "Winston Churchill"
  },
  {
    "text": "Your attitude, not your aptitude, will determine your altitude.",
    "author": "Zig Ziglar"
}]