[  {
    "text": "Spend some time this weekend on home improvement improve your attitude toward your family.",
    "author": "Bo Bennett"
  },
  {
    "text": "We awaken in others the same attitude of mind we hold toward them.",
    "author": "Elbert Hubbard"
  },
  {
    "text": "There is little difference in people, but that little difference makes a big difference. That little difference is attitude. The big difference is whether it is positive or negative.",
    "author": "Robert Collier"
  },
  {
    "text": "Ability is what you're capable of doing. Motivation determines what you do. Attitude determines how well you do it.",
    "author": "Lou Holtz"
  },
  {
    "text": "The last of human freedoms - the ability to chose one's attitude in a given set of circumstances.",
    "author": "Viktor E. Frankl"
}]