[  {
    "text": "Laughter is not a bad beginning for a friendship, and it is the best ending for one.",
    "author": "Henry Ward Beecher"
  },
  {
    "text": "What we call wisdom is the result of all the wisdom of past ages. Our best institutions are like young trees growing upon the roots of the old trunks that have crumbled away.",
    "author": "Henry Ward Beecher"
  },
  {
    "text": "The best way of removing negativity is to laugh and be joyous.",
    "author": "David Icke"
  },
  {
    "text": "Every year of my life I grow more convinced that it is wisest and best to fix our attention on the beautiful and the good, and dwell as little as possible on the evil and the false.",
    "author": "Richard Cecil"
  },
  {
    "text": "Men are like wine - some turn to vinegar, but the best improve with age.",
    "author": "Pope John XXIII"
}]