[  {
    "text": "No man who worships education has got the best out of education... Without a gentle contempt for education no man's education is complete.",
    "author": "Gilbert K. Chesterton"
  },
  {
    "text": "Use what talents you possess the woods would be very silent if no birds sang there except those that sang best.",
    "author": "Henry Van Dyke"
  },
  {
    "text": "A woman's best protection is a little money of her own.",
    "author": "Clare Boothe Luce"
  },
  {
    "text": "People who lean on logic and philosophy and rational exposition end by starving the best part of the mind.",
    "author": "William Butler Yeats"
  },
  {
    "text": "The most basic question is not what is best, but who shall decide what is best.",
    "author": "Thomas Sowell"
}]