[  {
    "text": "The public has lost faith in the ability of Social Security and Medicare to provide for old age. They've lost faith in the banking system and in conventional medical insurance.",
    "author": "Ron Chernow"
  },
  {
    "text": "Five thousand people every day lose their home because of a medical bankruptcy. Most of them had insurance.",
    "author": "Debbie Stabenow"
  },
  {
    "text": "Medical professionals, not insurance company bureaucrats, should be making health care decisions.",
    "author": "Barbara Boxer"
  },
  {
    "text": "We have the greatest hospitals, doctors, and medical technology in the world - we need to make them accessible to every American.",
    "author": "Barbara Boxer"
  },
  {
    "text": "Remember, I'm a doctor's daughter. So obviously I'm interested in all medical things.",
    "author": "Nancy Reagan"
}]